LimeNDAX/__init__.py
LimeNDAX/ndax_basic.py
LimeNDAX/ndax_functions.py
LimeNDAX-1.0.3.dist-info/METADATA
LimeNDAX-1.0.3.dist-info/WHEEL
LimeNDAX-1.0.3.dist-info/top_level.txt
LimeNDAX-1.0.3.dist-info/RECORD
