Metadata-Version: 2.1
Name: LimeNDAX
Version: 1.0.3
Summary: Python Package for working with NDAX files (generated from NEWARE machines), developed by Lime.AI
Author-email: Lime AI Celltesting <celltesting@lime.ai>
Project-URL: Homepage, https://github.com/limeaicell/LimeNDAX
Project-URL: Bug Tracker, https://github.com/limeaicell/LimeNDAX/issues
Classifier: Programming Language :: Python :: 3
Requires-Python: >=3.9
Requires-Dist: pandas
Requires-Dist: numpy
Provides-Extra: dev
